{
  "unpublishedPage": {
    "name": "Book List",
    "slug": "book-list",
    "layouts": [
      {
        "viewMode": false,
        "dsl": {
          "widgetName": "MainContainer",
          "backgroundColor": "none",
          "rightColumn": 816,
          "snapColumns": 64,
          "detachFromLayout": true,
          "widgetId": "0",
          "topRow": 0,
          "bottomRow": 700,
          "containerStyle": "none",
          "snapRows": 70,
          "parentRowSpace": 1,
          "type": "CANVAS_WIDGET",
          "canExtend": true,
          "version": 50,
          "minHeight": 710,
          "parentColumnSpace": 1,
          "dynamicBindingPathList": [],
          "leftColumn": 0,
          "children": [
            {
              "widgetName": "Table1",
              "defaultPageSize": 0,
              "columnOrder": [
                "name",
                "rating"
              ],
              "isVisibleDownload": true,
              "dynamicPropertyPathList": [],
              "displayName": "Table",
              "iconSVG": "/static/media/icon.db8a9cbd.svg",
              "topRow": 23,
              "bottomRow": 51,
              "isSortable": true,
              "parentRowSpace": 10,
              "type": "TABLE_WIDGET",
              "defaultSelectedRow": "0",
              "hideCard": false,
              "animateLoading": true,
              "parentColumnSpace": 12.5625,
              "dynamicTriggerPathList": [],
              "dynamicBindingPathList": [
                {
                  "key": "tableData"
                },
                {
                  "key": "primaryColumns.name.computedValue"
                },
                {
                  "key": "primaryColumns.rating.computedValue"
                }
              ],
              "leftColumn": 3,
              "primaryColumns": {
                "name": {
                  "index": 0,
                  "width": 150,
                  "id": "name",
                  "horizontalAlignment": "LEFT",
                  "verticalAlignment": "CENTER",
                  "columnType": "text",
                  "textSize": "PARAGRAPH",
                  "enableFilter": true,
                  "enableSort": true,
                  "isVisible": true,
                  "isDisabled": false,
                  "isCellVisible": true,
                  "isDerived": false,
                  "label": "name",
                  "computedValue": "{{Table1.sanitizedTableData.map((currentRow) => ( currentRow.name))}}"
                },
                "rating": {
                  "index": 1,
                  "width": 150,
                  "id": "rating",
                  "horizontalAlignment": "LEFT",
                  "verticalAlignment": "CENTER",
                  "columnType": "text",
                  "textSize": "PARAGRAPH",
                  "enableFilter": true,
                  "enableSort": true,
                  "isVisible": true,
                  "isDisabled": false,
                  "isCellVisible": true,
                  "isDerived": false,
                  "label": "rating",
                  "computedValue": "{{Table1.sanitizedTableData.map((currentRow) => ( currentRow.rating))}}"
                }
              },
              "delimiter": ",",
              "key": "7fjrcvsrpg",
              "derivedColumns": {},
              "rightColumn": 37,
              "textSize": "PARAGRAPH",
              "widgetId": "5qiftl87gy",
              "isVisibleFilters": true,
              "tableData": "{{get_book_list.data}}",
              "isVisible": true,
              "label": "Data",
              "searchKey": "",
              "enableClientSideSearch": true,
              "version": 3,
              "totalRecordsCount": 0,
              "parentId": "0",
              "renderMode": "CANVAS",
              "isLoading": false,
              "horizontalAlignment": "LEFT",
              "isVisibleSearch": true,
              "isVisiblePagination": true,
              "verticalAlignment": "CENTER",
              "columnSizeMap": {
                "task": 245,
                "step": 62,
                "status": 75
              }
            }
          ]
        },
        "layoutOnLoadActions": [
          [
            {
              "id": "Book List_get_book_list",
              "name": "get_book_list",
              "pluginType": "DB",
              "jsonPathKeys": [],
              "timeoutInMillisecond": 10000
            }
          ]
        ],
        "widgetNames": [
          "MainContainer",
          "Table1"
        ],
        "validOnPageLoadActions": true,
        "id": "Book List",
        "deleted": false,
        "policies": [],
        "userPermissions": []
      }
    ],
    "userPermissions": [],
    "policies": [],
    "isHidden": false
  },
  "publishedPage": {
    "name": "Book List",
    "slug": "book-list",
    "layouts": [
      {
        "viewMode": false,
        "dsl": {
          "widgetName": "MainContainer",
          "backgroundColor": "none",
          "rightColumn": 816,
          "snapColumns": 64,
          "detachFromLayout": true,
          "widgetId": "0",
          "topRow": 0,
          "bottomRow": 700,
          "containerStyle": "none",
          "snapRows": 70,
          "parentRowSpace": 1,
          "type": "CANVAS_WIDGET",
          "canExtend": true,
          "version": 50,
          "minHeight": 710,
          "parentColumnSpace": 1,
          "dynamicBindingPathList": [],
          "leftColumn": 0,
          "children": [
            {
              "widgetName": "Table1",
              "defaultPageSize": 0,
              "columnOrder": [
                "name",
                "rating"
              ],
              "isVisibleDownload": true,
              "dynamicPropertyPathList": [],
              "displayName": "Table",
              "iconSVG": "/static/media/icon.db8a9cbd.svg",
              "topRow": 23,
              "bottomRow": 51,
              "isSortable": true,
              "parentRowSpace": 10,
              "type": "TABLE_WIDGET",
              "defaultSelectedRow": "0",
              "hideCard": false,
              "animateLoading": true,
              "parentColumnSpace": 12.5625,
              "dynamicTriggerPathList": [],
              "dynamicBindingPathList": [
                {
                  "key": "tableData"
                },
                {
                  "key": "primaryColumns.name.computedValue"
                },
                {
                  "key": "primaryColumns.rating.computedValue"
                }
              ],
              "leftColumn": 3,
              "primaryColumns": {
                "name": {
                  "index": 0,
                  "width": 150,
                  "id": "name",
                  "horizontalAlignment": "LEFT",
                  "verticalAlignment": "CENTER",
                  "columnType": "text",
                  "textSize": "PARAGRAPH",
                  "enableFilter": true,
                  "enableSort": true,
                  "isVisible": true,
                  "isDisabled": false,
                  "isCellVisible": true,
                  "isDerived": false,
                  "label": "name",
                  "computedValue": "{{Table1.sanitizedTableData.map((currentRow) => ( currentRow.name))}}"
                },
                "rating": {
                  "index": 1,
                  "width": 150,
                  "id": "rating",
                  "horizontalAlignment": "LEFT",
                  "verticalAlignment": "CENTER",
                  "columnType": "text",
                  "textSize": "PARAGRAPH",
                  "enableFilter": true,
                  "enableSort": true,
                  "isVisible": true,
                  "isDisabled": false,
                  "isCellVisible": true,
                  "isDerived": false,
                  "label": "rating",
                  "computedValue": "{{Table1.sanitizedTableData.map((currentRow) => ( currentRow.rating))}}"
                }
              },
              "delimiter": ",",
              "key": "7fjrcvsrpg",
              "derivedColumns": {},
              "rightColumn": 37,
              "textSize": "PARAGRAPH",
              "widgetId": "5qiftl87gy",
              "isVisibleFilters": true,
              "tableData": "{{get_book_list.data}}",
              "isVisible": true,
              "label": "Data",
              "searchKey": "",
              "enableClientSideSearch": true,
              "version": 3,
              "totalRecordsCount": 0,
              "parentId": "0",
              "renderMode": "CANVAS",
              "isLoading": false,
              "horizontalAlignment": "LEFT",
              "isVisibleSearch": true,
              "isVisiblePagination": true,
              "verticalAlignment": "CENTER",
              "columnSizeMap": {
                "task": 245,
                "step": 62,
                "status": 75
              }
            }
          ]
        },
        "layoutOnLoadActions": [
          [
            {
              "id": "Book List_get_book_list",
              "name": "get_book_list",
              "pluginType": "DB",
              "jsonPathKeys": [],
              "timeoutInMillisecond": 10000
            }
          ]
        ],
        "widgetNames": [
          "MainContainer",
          "Table1"
        ],
        "validOnPageLoadActions": true,
        "id": "Book List",
        "deleted": false,
        "policies": [],
        "userPermissions": []
      }
    ],
    "userPermissions": [],
    "policies": [],
    "isHidden": false
  },
  "deleted": false,
  "policies": [],
  "userPermissions": [
    "read:pages",
    "manage:pages"
  ],
  "gitSyncId": "61e9557c7c4eab21b686c019_61e9591f7c4eab21b686c074"
}